<?xml version='1.0' encoding='UTF-8'?>
<igsSiteLog xmlns:equip="http://sopac.ucsd.edu/ns/geodesy/doc/igsSiteLog/equipment/2004" xmlns:contact="http://sopac.ucsd.edu/ns/geodesy/doc/igsSiteLog/contact/2004" xmlns:mi="http://sopac.ucsd.edu/ns/geodesy/doc/igsSiteLog/monumentInfo/2004" xmlns:li="http://sopac.ucsd.edu/ns/geodesy/doc/igsSiteLog/localInterferences/2004" xmlns="http://sopac.ucsd.edu/ns/geodesy/doc/igsSiteLog/2011" xmlns:xsi="http://www.w3.org/2001/XMLSchema-instance" xsi:schemaLocation="http://sopac.ucsd.edu/ns/geodesy/doc/igsSiteLog/2011 http://sopac.ucsd.edu/ns/geodesy/doc/igsSiteLog/2011/igsSiteLog.xsd">
  <formInformation>
    <mi:preparedBy>Elisabetta D'Anastasio</mi:preparedBy>
    <mi:datePrepared>2016-04-18</mi:datePrepared>
    <mi:reportType>DYNAMIC</mi:reportType>
  </formInformation>
  <siteIdentification>
    <mi:siteName>Utiku Reference Station</mi:siteName>
    <mi:fourCharacterID>UTKU</mi:fourCharacterID>
    <mi:monumentInscription></mi:monumentInscription>
    <mi:iersDOMESNumber></mi:iersDOMESNumber>
    <mi:cdpNumber></mi:cdpNumber>
    <mi:monumentDescription>mast</mi:monumentDescription>
    <mi:heightOfTheMonument></mi:heightOfTheMonument>
    <mi:monumentFoundation>stainless steel rod</mi:monumentFoundation>
    <mi:foundationDepth></mi:foundationDepth>
    <mi:markerDescription>Forced Centering</mi:markerDescription>
    <mi:dateInstalled>2008-11-12T00:00Z</mi:dateInstalled>
    <mi:geologicCharacteristic></mi:geologicCharacteristic>
    <mi:bedrockType></mi:bedrockType>
    <mi:bedrockCondition></mi:bedrockCondition>
    <mi:fractureSpacing></mi:fractureSpacing>
    <mi:faultZonesNearby></mi:faultZonesNearby>
    <mi:distance-Activity></mi:distance-Activity>
    <mi:notes></mi:notes>
  </siteIdentification>
  <siteLocation>
    <mi:city>Utiku Micklesons Farm</mi:city>
    <mi:state>Wellington</mi:state>
    <mi:country>New Zealand</mi:country>
    <mi:tectonicPlate>Australian</mi:tectonicPlate>
    <mi:approximatePositionITRF>
      <mi:xCoordinateInMeters>-4898205.48487</mi:xCoordinateInMeters>
      <mi:yCoordinateInMeters>357005.873666</mi:yCoordinateInMeters>
      <mi:zCoordinateInMeters>-4056599.68818</mi:zCoordinateInMeters>
      <mi:latitude-North>-39.745423558</mi:latitude-North>
      <mi:longitude-East>175.831366308</mi:longitude-East>
      <mi:elevation-m_ellips.>481.028</mi:elevation-m_ellips.>
    </mi:approximatePositionITRF>
    <mi:notes></mi:notes>
  </siteLocation>
  <gnssReceiver>
    <equip:receiverType>TRIMBLE NETRS</equip:receiverType>
    <equip:satelliteSystem>GPS</equip:satelliteSystem>
    <equip:serialNumber>4438238764</equip:serialNumber>
    <equip:firmwareVersion>1.2-0</equip:firmwareVersion>
    <equip:elevationCutoffSetting>4</equip:elevationCutoffSetting>
    <equip:dateInstalled>2008-11-12T03:00Z</equip:dateInstalled>
    <equip:dateRemoved>2011-04-20T02:00Z</equip:dateRemoved>
    <equip:temperatureStabilization></equip:temperatureStabilization>
    <equip:notes></equip:notes>
  </gnssReceiver>
  <gnssReceiver>
    <equip:receiverType>TRIMBLE NETR9</equip:receiverType>
    <equip:satelliteSystem>GPS+GLO</equip:satelliteSystem>
    <equip:serialNumber>5049K72301</equip:serialNumber>
    <equip:firmwareVersion>4.17</equip:firmwareVersion>
    <equip:elevationCutoffSetting>3</equip:elevationCutoffSetting>
    <equip:dateInstalled>2011-04-20T03:40Z</equip:dateInstalled>
    <equip:dateRemoved>2016-04-05T01:30Z</equip:dateRemoved>
    <equip:temperatureStabilization></equip:temperatureStabilization>
    <equip:notes></equip:notes>
  </gnssReceiver>
  <gnssReceiver>
    <equip:receiverType>TRIMBLE NETR9</equip:receiverType>
    <equip:satelliteSystem>GPS+GLO</equip:satelliteSystem>
    <equip:serialNumber>5049K72301</equip:serialNumber>
    <equip:firmwareVersion>4.85</equip:firmwareVersion>
    <equip:elevationCutoffSetting>0</equip:elevationCutoffSetting>
    <equip:dateInstalled>2016-04-05T01:30Z</equip:dateInstalled>
    <equip:dateRemoved></equip:dateRemoved>
    <equip:temperatureStabilization></equip:temperatureStabilization>
    <equip:notes></equip:notes>
  </gnssReceiver>
  <gnssAntenna>
    <equip:antennaType>TRM41249.00</equip:antennaType>
    <equip:serialNumber>12668980</equip:serialNumber>
    <equip:antennaReferencePoint>BAM</equip:antennaReferencePoint>
    <equip:marker-arpUpEcc.>0.0000</equip:marker-arpUpEcc.>
    <equip:marker-arpNorthEcc.>0.0000</equip:marker-arpNorthEcc.>
    <equip:marker-arpEastEcc.>0.0000</equip:marker-arpEastEcc.>
    <equip:alignmentFromTrueNorth>0</equip:alignmentFromTrueNorth>
    <equip:antennaRadomeType>NONE</equip:antennaRadomeType>
    <equip:radomeSerialNumber></equip:radomeSerialNumber>
    <equip:antennaCableType></equip:antennaCableType>
    <equip:antennaCableLength></equip:antennaCableLength>
    <equip:dateInstalled>2008-11-12T03:00Z</equip:dateInstalled>
    <equip:dateRemoved></equip:dateRemoved>
    <equip:notes></equip:notes>
  </gnssAntenna>
  <contactAgency>
    <contact:agency>GNS Science</contact:agency>
    <contact:preferredAbbreviation>GNS</contact:preferredAbbreviation>
    <contact:mailingAddress>1 Fairway Drive, Avalon 5010, PO Box 30-368, Lower Hutt, New Zealand</contact:mailingAddress>
    <contact:primaryContact>
      <contact:name>GeoNet reception</contact:name>
      <contact:telephonePrimary>+64 4 570 1444</contact:telephonePrimary>
      <contact:telephoneSecondary></contact:telephoneSecondary>
      <contact:fax>+64 4 570 4676</contact:fax>
      <contact:e-mail>info@geonet.org.nz</contact:e-mail>
    </contact:primaryContact>
    <contact:secondaryContact>
      <contact:name>Elisabetta D'Anastasio</contact:name>
      <contact:telephonePrimary>+64 4 570 4744</contact:telephonePrimary>
      <contact:telephoneSecondary></contact:telephoneSecondary>
      <contact:fax></contact:fax>
      <contact:e-mail>e.danastasio@gns.cri.nz</contact:e-mail>
    </contact:secondaryContact>
    <contact:notes></contact:notes>
  </contactAgency>
  <moreInformation>
    <mi:primaryDataCenter>ftp.geonet.org.nz</mi:primaryDataCenter>
    <mi:secondaryDataCenter></mi:secondaryDataCenter>
    <mi:urlForMoreInformation>www.geonet.org.nz</mi:urlForMoreInformation>
    <mi:hardCopyOnFile></mi:hardCopyOnFile>
    <mi:siteMap></mi:siteMap>
    <mi:siteDiagram></mi:siteDiagram>
    <mi:horizonMask></mi:horizonMask>
    <mi:monumentDescription></mi:monumentDescription>
    <mi:sitePictures></mi:sitePictures>
    <mi:notes>additional information and pictures could be found at http://magma.geonet.org.nz/delta/app then search for CGPS mark</mi:notes>
    <mi:antennaGraphicsWithDimensions>
TRM41249.00

   / --------------------------------------------- \
  +                                                 +
   \ --------------------------------------------- /
                   \               /
                    \             /
                     \-----x-----/                        &lt;--  0.0000  BAM=ARP
                                                                       RXC=NRP
  &lt;--                    0.3396                   --&gt;                  Notches
</mi:antennaGraphicsWithDimensions>
    <mi:insertTextGraphicFromAntenna></mi:insertTextGraphicFromAntenna>
  </moreInformation>
</igsSiteLog>
